Workbook

Sheet Cover Sheet
A1: ITC LIMITED
A2: Financial Performance Analysis & Simplified DCF Valuation
A4: Prepared by: | B4: Mohammed Noorani
A5: Institution: | B5: MIT Bengaluru
A6: Year: | B6: 2026
A8: ABOUT ITC LIMITED
A9: Established in 1910, ITC is a diversified Indian conglomerate and India's largest cigarette manufacturer. It operates across four reporting segments: FMCG-Cigarettes, FMCG-Others (foods, personal care, stationery, etc.), Paperboards, Paper & Packaging, and Agri Business. ITC demerged its Hotels business (ITC Hotels Ltd) as a separately listed company, effective January 2025 - this is an important corporate action that affects year-on-year comparability and is discussed in the Assumptions and Income Statement notes.
A14: SHEETS INCLUDED
A15: 1. Assumptions - forecast drivers and WACC inputs
A16: 2. Income Statement (FY21-FY26)
A17: 3. Balance Sheet (FY21-FY26)
A18: 4. Cash Flow (FY21-FY26, Operating CF derived from Net Profit)
A19: 5. Ratio Analysis - profitability, leverage, valuation ratios
A20: 6. DCF Valuation - WACC, 5-yr FCF forecast, terminal value, implied price
A21: 7. Peer Comparison - ITC vs Godfrey Phillips India vs HUL
A24: DATA SOURCES
A25: Historical financials: Screener.in (consolidated), accessed 18 Sep 2026
... A31: This is a simplified, Finance Model Analysis Project. Blue text = hardcoded inputs. Black text = formulas. Green text = links to another sheet. All figures are Rs Crore (consolidated) unless stated otherwise.

Sheet Assumptions
A1: ITC - Model Assumptions
A2: All blue cells are inputs, sourced and dated. Do not hardcode these numbers anywhere else.
A4: FORECAST DRIVERS (FY27-FY31)
A5: Revenue Growth % | B5: 0.08 | C5: Moderated vs. 9.9% historical 5-yr CAGR (which included a low FY21 COVID base)
A6: EBIT Margin % (Operating Margin) | B6: 0.35 | C6: In line with FY21-26 average OPM of ~35%, driven by high-margin cigarette segment
A7: Tax Rate | B7: 0.25 | C7: Normalized effective tax rate (FY25's 16% was a one-off, related to demerger accounting)
A8: Depreciation Growth % | B8: 0.05
A9: Capex Growth % | B9: 0.04
A10: Change in Working Capital (Rs Cr) | B10: 300
A13: WACC INPUTS
A14: Risk-Free Rate (Rf) | B14: 0.071 | C14: India 10Y G-Sec, ~7.1%, TradingEconomics, 15 Sep 2026
A15: Beta | B15: 0.35 | C15: ITC 1-yr beta ~0.34-0.35 (low-beta defensive staple), TradingView, 2026
A16: Equity Risk Premium (ERP) | B16: 0.06 | C16: Approx. Damodaran India ERP (mature-market ERP ~4.2% + India country risk premium), 2026
A17: Cost of Equity (Ke) = Rf + Beta x ERP | B17: =B14+(B15*B16) -> 0.092
A18: Cost of Debt (Pre-tax) | B18: 0.075 | C18: Approximate, given ITC's negligible borrowings
A19: Cost of Debt (Post-tax) = Kd x (1-tax) | B19: =B18*(1-B7) -> 0.05625
A22: VALUATION INPUTS
A23: Terminal Growth Rate | B23: 0.05
A24: Current Market Price, CMP (Rs) | B24: 262 | C24: Screener.in close price, 18 Sep 2026
A25: Shares Outstanding (Cr) | B25: 1254.5 | C25: Market Cap Rs 3,28,675 Cr / CMP Rs 262, Screener.in, 18 Sep 2026
A28: IMPORTANT NOTE: ITC Hotels Demerger
A29: ITC demerged its Hotels business effective Jan 2025. This caused a one-off Rs 17,803 Cr Other Income spike in FY25 (demerger-related gain) and a drop in Fixed Assets from Rs 27,820 Cr (FY24) to Rs 21,955 Cr (FY25) as hotel properties left the balance sheet. FY24 revenue also reflects a restatement for discontinued operations. All figures here are taken directly from Screener.in's published consolidated series on a consistent basis; no numbers have been mixed across standalone/consolidated definitions.

Sheet Income Statement
A1: ITC Limited - Income Statement (Rs Cr, Consolidated)
A3: Particulars | B3: FY21 | C3: FY22 | D3: FY23 | E3: FY24 | F3: FY25 | G3: FY26
A4: Sales | B4: 49257 | C4: 60645 | D4: 70919 | E4: 67932 | F4: 75323 | G4: 78868
A5: Expenses | B5: 32193 | C5: 40021 | D5: 45215 | E5: 42744 | F5: 49492 | G5: 51562
A6: Operating Profit (EBIT) | B6: =B4-B5 -> 17064 | C6: =C4-C5 -> 20624 | D6: =D4-D5 -> 25704 | E6: =E4-E5 -> 25188 | F6: =F4-F5 -> 25831 | G6: =G4-G5 -> 27306
A7: OPM % (EBIT Margin) | B7: =B6/B4 -> 0.34642792 | C7: =C6/C4 -> 0.3400775 | D7: =D6/D4 -> 0.36244166 | E7: =E6/E4 -> 0.37078255 | F7: =F6/F4 -> 0.34293642 | G7: =G6/G4 -> 0.34622407
A8: Other Income | B8: 2577 | C8: 1910 | D8: 2098 | E8: 3330 | F8: 17803 | G8: 2523
A9: Interest | B9: 58 | C9: 60 | D9: 78 | E9: 39 | F9: 45 | G9: 85
A10: Depreciation | B10: 1646 | C10: 1732 | D10: 1809 | E10: 1518 | F10: 1646 | G10: 1711
A11: Profit Before Tax | B11: =B6+B8-B9-B10 -> 17937 | C11: =C6+C8-C9-C10 -> 20742 | D11: =D6+D8-D9-D10 -> 25915 | E11: =E6+E8-E9-E10 -> 26961 | F11: =F6+F8-F9-F10 -> 41943 | G11: =G6+G8-G9-G10 -> 28033
A12: Tax % (derived) | B12: =1-(B13/B11) -> 0.25388861 | C12: =1-(C13/C11) -> 0.25257931 | D12: =1-(D13/D11) -> 0.24842755 | E12: =1-(E13/E11) -> 0.2303327 | F12: =1-(F13/F11) -> 0.1642944 | G12: =1-(G13/G11) -> 0.25024079
A13: Net Profit | B13: 13383 | C13: 15503 | D13: 19477 | E13: 20751 | F13: 35052 | G13: 21018
A14: EPS (Rs) | B14: 10.69 | C14: 12.37 | D14: 15.44 | E14: 16.39 | F14: 27.77 | G14: 16.51
A16: NOTE: FY25 Anomaly
A17: FY25's Other Income of Rs 17,803 Cr includes a one-off gain related to the ITC Hotels demerger (completed Jan 2025). This inflated FY25 Net Profit to Rs 35,052 Cr; excluding it, underlying profit growth was far more modest. See Python analysis for a full breakdown.
A20: GROWTH & MARGIN ANALYSIS
A21: Sales YoY Growth % | C21: =(C4/B4)-1 -> 0.23119557 | D21: =(D4/C4)-1 -> 0.16941215 | E21: =(E4/D4)-1 -> -0.042118473 | F21: =(F4/E4)-1 -> 0.10879998 | G21: =(G4/F4)-1 -> 0.047063978
A22: Net Profit YoY Growth % | C22: =(C13/B13)-1 -> 0.15840992 | D22: =(D13/C13)-1 -> 0.25633748 | E22: =(E13/D13)-1 -> 0.065410484 | F22: =(F13/E13)-1 -> 0.68917161 | G22: =(G13/F13)-1 -> -0.40037658
A23: Net Profit Margin % | B23: =B13/B4 -> 0.27169742 | C23: =C13/C4 -> 0.25563525 | D23: =D13/D4 -> 0.27463726 | E23: =E13/E4 -> 0.30546723 | F23: =F13/F4 -> 0.46535587 | G23: =G13/G4 -> 0.26649592
A25: Sales 5-Yr CAGR (FY21-FY26) | B25: =(G4/B4)^(1/5)-1 -> 0.098718846
A26: Net Profit 5-Yr CAGR (FY21-FY26) | B26: =(G13/B13)^(1/5)-1 -> 0.094479375

Sheet Balance Sheet
A1: ITC Limited - Balance Sheet (Rs Cr, Consolidated)
A3: Particulars | B3: FY21 | C3: FY22 | D3: FY23 | E3: FY24 | F3: FY25 | G3: FY26
A4: ASSETS
A5: Fixed Assets | B5: 23298 | C5: 24232 | D5: 25851 | E5: 27820 | F5: 21955 | G5: 22443
A6: Capital Work in Progress (CWIP) | B6: 4011 | C6: 3226 | D6: 3003 | E6: 2861 | F6: 1091 | G6: 1602
A7: Investments | B7: 24871 | C7: 24841 | D7: 29415 | E7: 31114 | F7: 34720 | G7: 38128
A8: Other Assets | B8: 21580 | C8: 24898 | D8: 27561 | E8: 29959 | F8: 30237 | G8: 31464
A9: Total Assets | B9: =SUM(B5:B8) -> 73760 | C9: =SUM(C5:C8) -> 77197 | D9: =SUM(D5:D8) -> 85830 | E9: =SUM(E5:E8) -> 91754 | F9: =SUM(F5:F8) -> 88003 | G9: =SUM(G5:G8) -> 93637
A11: EQUITY
A12: Share Capital | B12: 1231 | C12: 1232 | D12: 1243 | E12: 1248 | F12: 1251 | G12: 1253
A13: Reserves & Surplus | B13: 59116 | C13: 61223 | D13: 67912 | E13: 73259 | F13: 68779 | G13: 71254
A14: Total Equity | B14: =SUM(B12:B13) -> 60347 | C14: =SUM(C12:C13) -> 62455 | D14: =SUM(D12:D13) -> 69155 | E14: =SUM(E12:E13) -> 74507 | F14: =SUM(F12:F13) -> 70030 | G14: =SUM(G12:G13) -> 72507
A16: LIABILITIES
A17: Borrowings | B17: 271 | C17: 249 | D17: 306 | E17: 303 | F17: 285 | G17: 2399
A18: Other Liabilities | B18: 13143 | C18: 14491 | D18: 16370 | E18: 16944 | F18: 17688 | G18: 18731
A19: Total Liabilities | B19: =SUM(B17:B18) -> 13414 | C19: =SUM(C17:C18) -> 14740 | D19: =SUM(D17:D18) -> 16676 | E19: =SUM(E17:E18) -> 17247 | F19: =SUM(F17:F18) -> 17973 | G19: =SUM(G17:G18) -> 21130
A21: Total Equity + Liabilities (check) | B21: =B14+B19 -> 73761 | C21: =C14+C19 -> 77195 | D21: =D14+D19 -> 85831 | E21: =E14+E19 -> 91754 | F21: =F14+F19 -> 88003 | G21: =G14+G19 -> 93637
A22: Balance Check (should be 0) | B22: =B9-B21 -> -1 | C22: =C9-C21 -> 2 | D22: =D9-D21 -> -1 | E22: =E9-E21 -> 0 | F22: =F9-F21 -> 0 | G22: =G9-G21 -> 0
A24: NOTE
A25: Fixed Assets fall from Rs 27,820 Cr (FY24) to Rs 21,955 Cr (FY25) because hotel properties left the balance sheet on demerger. Borrowings jump in FY26 mainly reflects lease-liability reclassification, not new debt - ITC remains effectively debt-free. The balance check shows a Rs 1-2 Cr gap in some years (out of ~Rs 90,000 Cr total assets) - this comes from Screener.in's individually-rounded line items not summing perfectly to its own reported Total Assets figure. This is a real, expected artifact of using rounded third-party aggregated data, not a modeling error - flagged here rather than silently adjusted, per the project's data-consistency principle.

Sheet Cash Flow
A1: ITC Limited - Cash Flow Statement (Rs Cr, Consolidated)
A3: Particulars | B3: FY21 | C3: FY22 | D3: FY23 | E3: FY24 | F3: FY25 | G3: FY26
A4: Cash from Operations (derived) | B4: ='Income Statement'!B13+'Income Statement'!B10 -> 15029 | C4: ='Income Statement'!C13+'Income Statement'!C10 -> 17235 | D4: ='Income Statement'!D13+'Income Statement'!D10 -> 21286 | E4: ='Income Statement'!E13+'Income Statement'!E10 -> 22269 | F4: ='Income Statement'!F13+'Income Statement'!F10 -> 36698 | G4: ='Income Statement'!G13+'Income Statement'!G10 -> 22729
A5: = Net Profit + Depreciation
A6: Cash from Investing | B6: 5740 | C6: -2238 | D6: -5732 | E6: 1563 | F6: -564 | G6: -2321
A7: Cash from Financing | B7: -18634 | C7: -13580 | D7: -13006 | E7: -18551 | F7: -17037 | G7: -16147
A8: Net Change in Cash | B8: =B4+B6+B7 -> 2135 | C8: =C4+C6+C7 -> 1417 | D8: =D4+D6+D7 -> 2548 | E8: =E4+E6+E7 -> 5281 | F8: =F4+F6+F7 -> 19097 | G8: =G4+G6+G7 -> 4261
A10: NOTE
A11: Operating Cash Flow here is derived (Net Profit + Depreciation added back) rather than typed in from Screener, to demonstrate understanding of why depreciation is a non-cash add-back. It will not exactly match Screener's reported CFO (which also adjusts for working capital and other items) - that is expected and is explained in the README. Cash from Investing for ITC includes large treasury/investment-portfolio movements (ITC holds a large investment book), not just capex, so it is a rough capex proxy only.

Sheet Ratio Analysis
A1: ITC Limited - Ratio Analysis
A3: Particulars | B3: FY21 | C3: FY22 | D3: FY23 | E3: FY24 | F3: FY25 | G3: FY26 | H3: Formula Used
A4: PROFITABILITY RATIOS
A5: Net Profit Margin % | B5: ='Income Statement'!B13/'Income Statement'!B4 -> 0.27169742 | C5: ='Income Statement'!C13/'Income Statement'!C4 -> 0.25563525 | D5: ='Income Statement'!D13/'Income Statement'!D4 -> 0.27463726 | E5: ='Income Statement'!E13/'Income Statement'!E4 -> 0.30546723 | F5: ='Income Statement'!F13/'Income Statement'!F4 -> 0.46535587 | G5: ='Income Statement'!G13/'Income Statement'!G4 -> 0.26649592 | H5: Net Profit / Sales
A6: EBITDA Margin % | B6: =('Income Statement'!B6+'Income Statement'!B10)/'Income Statement'!B4 -> 0.37984449 | C6: =('Income Statement'!C6+'Income Statement'!C10)/'Income Statement'!C4 -> 0.36863715 | D6: =('Income Statement'!D6+'Income Statement'!D10)/'Income Statement'!D4 -> 0.38794963 | E6: =('Income Statement'!E6+'Income Statement'!E10)/'Income Statement'!E4 -> 0.39312842 | F6: =('Income Statement'!F6+'Income Statement'!F10)/'Income Statement'!F4 -> 0.36478898 | G6: =('Income Statement'!G6+'Income Statement'!G10)/'Income Statement'!G4 -> 0.36791855 | H6: (EBIT + Depreciation) / Sales
A7: Return on Equity (ROE) % | B7: ='Income Statement'!B13/'Balance Sheet'!B14 -> 0.22176744 | C7: ='Income Statement'!C13/'Balance Sheet'!C14 -> 0.24822672 | D7: ='Income Statement'!D13/'Balance Sheet'!D14 -> 0.28164269 | E7: ='Income Statement'!E13/'Balance Sheet'!E14 -> 0.27851074 | F7: ='Income Statement'!F13/'Balance Sheet'!F14 -> 0.50052834 | G7: ='Income Statement'!G13/'Balance Sheet'!G14 -> 0.28987546 | H7: Net Profit / Total Equity
A8: Return on Capital Employed (ROCE) % | B8: ='Income Statement'!B6/('Balance Sheet'!B9-'Balance Sheet'!B17) -> 0.23219802 | C8: ='Income Statement'!C6/('Balance Sheet'!C9-'Balance Sheet'!C17) -> 0.26802516 | D8: ='Income Statement'!D6/('Balance Sheet'!D9-'Balance Sheet'!D17) -> 0.30054721 | E8: ='Income Statement'!E6/('Balance Sheet'!E9-'Balance Sheet'!E17) -> 0.27542618 | F8: ='Income Statement'!F6/('Balance Sheet'!F9-'Balance Sheet'!F17) -> 0.29447776 | G8: ='Income Statement'!G6/('Balance Sheet'!G9-'Balance Sheet'!G17) -> 0.29928319 | H8: EBIT / (Total Assets - Borrowings)
A9: Return on Assets (ROA) % | B9: ='Income Statement'!B13/'Balance Sheet'!B9 -> 0.1814398 | C9: ='Income Statement'!C13/'Balance Sheet'!C9 -> 0.20082387 | D9: ='Income Statement'!D13/'Balance Sheet'!D9 -> 0.22692532 | E9: ='Income Statement'!E13/'Balance Sheet'!E9 -> 0.22615908 | F9: ='Income Statement'!F13/'Balance Sheet'!F9 -> 0.3983046 | G9: ='Income Statement'!G13/'Balance Sheet'!G9 -> 0.22446255 | H9: Net Profit / Total Assets
A11: LEVERAGE RATIOS
A12: Debt to Equity | B12: ='Balance Sheet'!B17/'Balance Sheet'!B14 -> 0.0044906955 | C12: ='Balance Sheet'!C17/'Balance Sheet'!C14 -> 0.0039868705 | D12: ='Balance Sheet'!D17/'Balance Sheet'!D14 -> 0.0044248427 | E12: ='Balance Sheet'!E17/'Balance Sheet'!E14 -> 0.004066732 | F12: ='Balance Sheet'!F17/'Balance Sheet'!F14 -> 0.0040696844 | G12: ='Balance Sheet'!G17/'Balance Sheet'!G14 -> 0.033086461 | H12: Borrowings / Total Equity
A13: Debt to Assets | B13: ='Balance Sheet'!B17/'Balance Sheet'!B9 -> 0.0036740781 | C13: ='Balance Sheet'!C17/'Balance Sheet'!C9 -> 0.0032255139 | D13: ='Balance Sheet'!D17/'Balance Sheet'!D9 -> 0.003565187 | E13: ='Balance Sheet'!E17/'Balance Sheet'!E9 -> 0.0033023083 | F13: ='Balance Sheet'!F17/'Balance Sheet'!F9 -> 0.003238526 | G13: ='Balance Sheet'!G17/'Balance Sheet'!G9 -> 0.025620214 | H13: Borrowings / Total Assets
A14: Interest Coverage Ratio | B14: ='Income Statement'!B6/'Income Statement'!B9 -> 294.2069 | C14: ='Income Statement'!C6/'Income Statement'!C9 -> 343.73333 | D14: ='Income Statement'!D6/'Income Statement'!D9 -> 329.53846 | E14: ='Income Statement'!E6/'Income Statement'!E9 -> 645.84615 | F14: ='Income Statement'!F6/'Income Statement'!F9 -> 574.02222 | G14: ='Income Statement'!G6/'Income Statement'!G9 -> 321.24706 | H14: EBIT / Interest Expense
A16: MARKET RATIOS (FY26, using current CMP)
A17: EPS (Rs) | G17: ='Income Statement'!G14 -> 16.51
A18: P/E Ratio | G18: =Assumptions!B24/'Income Statement'!G14 -> 15.86917 | H18: CMP / EPS
A19: P/B Ratio | G19: =(Assumptions!B24*Assumptions!B25)/'Balance Sheet'!G14 -> 4.5330658 | H19: Market Cap / Total Equity
A20: Dividend Yield % (FY26, reported) | G20: 0.0553 | H20: Reported by Screener.in, 18 Sep 2026 (not derivable from this workbook's data alone)
A22: WORKING CAPITAL (FY26, reported)
A23: Cash Conversion Cycle (days) | G23: 164 | H23: Debtor Days(18) + Inventory Days(209) - Payable Days(63), Screener.in. Not derivable from this simplified Balance Sheet, which does not separately break out receivables/inventory/payables.

Sheet DCF Valuation
A1: ITC Limited - Simplified DCF Valuation
A3: WACC
A4: Cost of Equity (Ke) | B4: =Assumptions!B17 -> 0.092
A5: Cost of Debt, post-tax (Kd) | B5: =Assumptions!B19 -> 0.05625
A6: Market Cap (Rs Cr) | B6: =Assumptions!B24*Assumptions!B25 -> 328679
A7: Total Debt (Rs Cr) | B7: ='Balance Sheet'!G17 -> 2399
A8: Equity Weight | B8: =B6/(B6+B7) -> 0.99275397
A9: Debt Weight | B9: =B7/(B6+B7) -> 0.0072460266
A10: WACC | B10: =(B4*B8)+(B5*B9) -> 0.091740955
A13: FREE CASH FLOW PROJECTION (Rs Cr)
B14: FY26 (Base) | C14: FY27 | D14: FY28 | E14: FY29 | F14: FY30 | G14: FY31
A15: Revenue | B15: ='Income Statement'!G4 -> 78868 | C15: =B15*(1+Assumptions!$B$5) -> 85177.44 | D15: =C15*(1+Assumptions!$B$5) -> 91991.635 | E15: =D15*(1+Assumptions!$B$5) -> 99350.966 | F15: =E15*(1+Assumptions!$B$5) -> 107299.04 | G15: =F15*(1+Assumptions!$B$5) -> 115882.97
A16: EBIT | B16: ='Income Statement'!G6 -> 27306 | C16: =C15*Assumptions!$B$6 -> 29812.104 | D16: =D15*Assumptions!$B$6 -> 32197.072 | E16: =E15*Assumptions!$B$6 -> 34772.838 | F16: =F15*Assumptions!$B$6 -> 37554.665 | G16: =G15*Assumptions!$B$6 -> 40559.038
A17: Tax on EBIT | B17: =B16*Assumptions!$B$7 -> 6826.5 | C17: =C16*Assumptions!$B$7 -> 7453.026 | D17: =D16*Assumptions!$B$7 -> 8049.2681 | E17: =E16*Assumptions!$B$7 -> 8693.2095 | F17: =F16*Assumptions!$B$7 -> 9388.6663 | G17: =G16*Assumptions!$B$7 -> 10139.76
A18: NOPAT | B18: =B16-B17 -> 20479.5 | C18: =C16-C17 -> 22359.078 | D18: =D16-D17 -> 24147.804 | E18: =E16-E17 -> 26079.629 | F18: =F16-F17 -> 28165.999 | G18: =G16-G17 -> 30419.279
A19: Add: Depreciation | B19: ='Income Statement'!G10 -> 1711 | C19: =B19*(1+Assumptions!$B$8) -> 1796.55 | D19: =C19*(1+Assumptions!$B$8) -> 1886.3775 | E19: =D19*(1+Assumptions!$B$8) -> 1980.6964 | F19: =E19*(1+Assumptions!$B$8) -> 2079.7312 | G19: =F19*(1+Assumptions!$B$8) -> 2183.7178
A20: Less: Capex (proxy: -Cash from Investing) | B20: =-'Cash Flow'!G6 -> 2321 | C20: =B20*(1+Assumptions!$B$9) -> 2413.84 | D20: =C20*(1+Assumptions!$B$9) -> 2510.3936 | E20: =D20*(1+Assumptions!$B$9) -> 2610.8093 | F20: =E20*(1+Assumptions!$B$9) -> 2715.2417 | G20: =F20*(1+Assumptions!$B$9) -> 2823.8514
A21: Less: Change in Working Capital | C21: =Assumptions!$B$10 -> 300 | D21: =Assumptions!$B$10 -> 300 | E21: =Assumptions!$B$10 -> 300 | F21: =Assumptions!$B$10 -> 300 | G21: =Assumptions!$B$10 -> 300
A22: Free Cash Flow (FCF) | C22: =C18+C19-C20-C21 -> 21441.788 | D22: =D18+D19-D20-D21 -> 23223.788 | E22: =E18+E19-E20-E21 -> 25149.516 | F22: =F18+F19-F20-F21 -> 27230.488 | G22: =G18+G19-G20-G21 -> 29479.145
A24: TERMINAL VALUE
A25: Terminal Value = FCF(FY31) x (1+g) / (WACC-g) | B25: =G22*(1+Assumptions!B23)/(B10-Assumptions!B23) -> 741552.34
A27: DISCOUNTING
A28: Discount Factor | C28: =1/(1+$B$10)^1 -> 0.9159682 | D28: =1/(1+$B$10)^2 -> 0.83899775 | E28: =1/(1+$B$10)^3 -> 0.76849526 | F28: =1/(1+$B$10)^4 -> 0.70391722 | G28: =1/(1+$B$10)^5 -> 0.64476579
A29: PV of FCF | C29: =C22*C28 -> 19639.996 | D29: =D22*D28 -> 19484.706 | E29: =E22*E28 -> 19327.284 | F29: =F22*F28 -> 19168.01 | G29: =G22*G28 -> 19007.144
A31: VALUATION SUMMARY
A32: Sum of PV of FCFs | B32: =SUM(C29:G29) -> 96627.14
A33: PV of Terminal Value | B33: =B25/(1+B10)^5 -> 478127.58
A34: Enterprise Value (EV) | B34: =B32+B33 -> 574754.72
A35: Less: Debt | B35: =B7 -> 2399
A36: Equity Value | B36: =B34-B35 -> 572355.72
A37: Shares Outstanding (Cr) | B37: =Assumptions!B25 -> 1254.5
A38: Implied Share Price (Rs) | B38: =B36/B37 -> 456.2421
A39: Current Market Price, CMP (Rs) | B39: =Assumptions!B24 -> 262
A40: Upside / (Downside) vs CMP % | B40: =(B38-B39)/B39 -> 0.74138208
A42: SIMPLE SENSITIVITY: Implied Price vs. WACC
A43: WACC -1% | B43: =((C22/(1+(B10-0.01))^1+D22/(1+(B10-0.01))^2+E22/(1+(B10-0.01))^3+F22/(1+(B10-0.01))^4+G22/(1+(B10-0.01))^5)+((G22*(1+Assumptions!B23)/((B10-0.01)-Assumptions!B23))/(1+(B10-0.01))^5)-B35)/B37 -> 602.06686
A44: WACC (base) | B44: =((C22/(1+B10)^1+D22/(1+B10)^2+E22/(1+B10)^3+F22/(1+B10)^4+G22/(1+B10)^5)+((G22*(1+Assumptions!B23)/(B10-Assumptions!B23))/(1+B10)^5)-B35)/B37 -> 456.2421
A45: WACC +1% | B45: =((C22/(1+(B10+0.01))^1+D22/(1+(B10+0.01))^2+E22/(1+(B10+0.01))^3+F22/(1+(B10+0.01))^4+G22/(1+(B10+0.01))^5)+((G22*(1+Assumptions!B23)/((B10+0.01)-Assumptions!B23))/(1+(B10+0.01))^5)-B35)/B37 -> 366.81722

Sheet Peer Comparison
A1: ITC Limited - Peer Comparison
A3: Source: Screener.in , Year:2026
A5: Metric | B5: ITC | C5: Godfrey Phillips India | D5: Hindustan Unilever (HUL)
A6: Revenue FY26 (Rs Cr) | B6: 78868 | C6: 6391 | D6: 64468
A7: Operating Margin FY26 % | B7: 0.346 | C7: 0.248 | D7: 0.233
A8: Net Profit Margin FY26 % | B8: 0.266 | C8: 0.239 | D8: 0.234
A9: ROE % (TTM) | B9: 0.293 | C9: 0.234 | D9: 0.309
A10: P/E Ratio (current) | B10: 16.6 | C10: 23 | D10: 48.6
A12: WHY THESE PEERS
A13: Godfrey Phillips India is chosen as a direct, pure-play cigarette-business peer (India's #2 domestic cigarette player after ITC) - useful for isolating how ITC's core tobacco economics compare without its FMCG/paperboard/agri diversification. Hindustan Unilever is chosen as the closest large-cap diversified FMCG peer, useful for comparing ITC's FMCG-Others ambitions against an established FMCG leader.
A18: INSIGHT
A19: ITC has the highest operating margin of the three companies but the lowest P/E ratio, highlighting a significant difference between operating profitability and market valuation.
